MANIFEST.in
README.md
__init__.py
local_setup.py
setup.cfg
setup.py
uninstall_MESA2HYDRO.py
DOCUMENTATION/Joyce_2019_ApJ_882_63.pdf
DOCUMENTATION/MESA2HYDRO_users_guide.pdf
DOCUMENTATION/README
DOCUMENTATION/usersguide.pdf
MESA2HYDRO.egg-info/PKG-INFO
MESA2HYDRO.egg-info/SOURCES.txt
MESA2HYDRO.egg-info/dependency_links.txt
MESA2HYDRO.egg-info/requires.txt
MESA2HYDRO.egg-info/top_level.txt
data/MESA_controls/controls.defaults
data/MESA_controls/history_columns.list
data/MESA_controls/history_columns_testsuite.list
data/MESA_controls/profile_columns.list
data/MESA_controls/profile_columns_testsuite.list
data/MESA_controls/star_job.defaults
data/config_file_examples/AGB.cfg
data/config_file_examples/OB.cfg
data/config_file_examples/mainsequence.cfg
data/config_file_examples/mainsequence_test.cfg
data/config_file_examples/redgiant.cfg
data/config_file_examples/wd1.cfg
data/config_file_examples/wd2.cfg
data/config_file_examples/wd3.cfg
data/inlists/agb.mod
data/inlists/agb2.mod
data/inlists/inlist_OB
data/inlists/inlist_OB_solarmet
data/inlists/inlist_OB_solarmet_trial
data/inlists/inlist_agb_forLMC
data/inlists/inlist_agb_from_mod_forLMC
data/inlists/inlist_agb_timmes
data/inlists/inlist_mainsequence
data/inlists/inlist_redgiant
data/inlists/inlist_tashibu
data/inlists/inlist_wd2
data/inlists/inlist_wd3
data/inlists/inlist_wd_0.6test
data/inlists/inlist_wd_from_mod
data/inlists/inlist_whitedwarf
data/inlists/wd1_0.6Msolar.mod
data/inlists/wd2_1Msolar.mod
data/inlists/wd3_1Msolar.mod
data/inlists/wd_disjoint_EOS.mod
data/sample_MESA_output/history_AGB_from_mod_logE.data
data/sample_MESA_output/history_OB_logE.data
data/sample_MESA_output/history_OB_solarmet.data
data/sample_MESA_output/history_agb_timmes_logE.data
data/sample_MESA_output/history_mainsequence_logE.data
data/sample_MESA_output/history_redgiant_logE.data
data/sample_MESA_output/history_wd2.data
data/sample_MESA_output/history_wd3_test.data
data/sample_MESA_output/history_wd_0.6test.data
data/sample_MESA_output/history_whitedwarf_logE.data
data/sample_MESA_output/profile_AGB_from_mod_logE.data
data/sample_MESA_output/profile_OB_fig44.data
