Metadata-Version: 1.0
Name: MESA2HYDRO
Version: 1.1.3
Summary: Convert 1D stellar structure models to 3D particle distributions using the HEALPix spherical tessellation algorithm
Home-page: https://github.com/mjoyceGR/MESA2HYDRO
Author: Meridith Joyce
Author-email: Meridith.Joyce@anu.edu.au
License: UNKNOWN
Keywords: MESA,stellar evolution,stellar structure,astronomy,stellar modeling,hydrodynamical ICs,HEALPix
Platform: UNKNOWN
